lemonpepper/PicovoiceOrcaStreamer.py
lemonpepper/__init__.py
lemonpepper/gui_textual.py
lemonpepper/gui_textual.tcss
lemonpepper/local_debug_import.py
lemonpepper/model_manager.py
lemonpepper/ollama_api.py
lemonpepper/spinners.json
lemonpepper/transcribe_audio.py
lemonpepper/transcribe_audio_google_cloud.py
lemonpepper/transcribe_audio_whisper.py
lemonpepper/utils.py
lemonpepper-0.2.4.dist-info/LICENSE
lemonpepper-0.2.4.dist-info/METADATA
lemonpepper-0.2.4.dist-info/WHEEL
lemonpepper-0.2.4.dist-info/entry_points.txt
lemonpepper-0.2.4.dist-info/top_level.txt
lemonpepper-0.2.4.dist-info/RECORD
