Metadata-Version: 2.2
Name: lemonpepper
Version: 0.2.4
Summary: A real-time audio transcription and AI interaction tool
Home-page: https://github.com/alexoms/lemonpepper
Author: Unidatum Integrated Products LLC
Author-email: alex.chang@unidatum.com
Classifier: Programming Language :: Python :: 3
Classifier: License :: OSI Approved :: Apache Software License
Classifier: Operating System :: OS Independent
Requires-Python: >=3.7
License-File: LICENSE
Requires-Dist: pywhispercpp
Requires-Dist: vosk
Requires-Dist: pvorca
Requires-Dist: numpy
Requires-Dist: sounddevice
Requires-Dist: webrtcvad
Requires-Dist: textual
Requires-Dist: textual-slider
Requires-Dist: ollama
Requires-Dist: pyperclip
Requires-Dist: rich
Requires-Dist: aiohttp
Requires-Dist: appdirs
Dynamic: author
Dynamic: author-email
Dynamic: classifier
Dynamic: description
Dynamic: description-content-type
Dynamic: home-page
Dynamic: requires-dist
Dynamic: requires-python
Dynamic: summary
